nf_sim/__init__.py
NFSim-0.2.1.dist-info/LICENSE
NFSim-0.2.1.dist-info/METADATA
NFSim-0.2.1.dist-info/WHEEL
NFSim-0.2.1.dist-info/top_level.txt
NFSim-0.2.1.dist-info/RECORD
